sphinx_theme_builder/__init__.py
sphinx_theme_builder/__main__.py
sphinx_theme_builder/testing.py
sphinx_theme_builder/_internal/__init__.py
sphinx_theme_builder/_internal/distributions.py
sphinx_theme_builder/_internal/errors.py
sphinx_theme_builder/_internal/nodejs.py
sphinx_theme_builder/_internal/passthrough.py
sphinx_theme_builder/_internal/project.py
sphinx_theme_builder/_internal/ui.py
sphinx_theme_builder/_internal/wheelfile.py
sphinx_theme_builder/_internal/.mypy_cache/.gitignore
sphinx_theme_builder/_internal/.mypy_cache/CACHEDIR.TAG
sphinx_theme_builder/_internal/.mypy_cache/3.11/@plugins_snapshot.json
sphinx_theme_builder/_internal/.mypy_cache/3.11/__future__.data.json
sphinx_theme_builder/_internal/.mypy_cache/3.11/__future__.meta.json
sphinx_theme_builder/_internal/.mypy_cache/3.11/_ast.data.json
sphinx_theme_builder/_internal/.mypy_cache/3.11/_ast.meta.json
sphinx_theme_builder/_internal/.mypy_cache/3.11/_codecs.data.json
sphinx_theme_builder/_internal/.mypy_cache/3.11/_codecs.meta.json
sphinx_theme_builder/_internal/.mypy_cache/3.11/_collections_abc.data.json
sphinx_theme_builder/_internal/.mypy_cache/3.11/_collections_abc.meta.json
sphinx_theme_builder/_internal/.mypy_cache/3.11/_compression.data.json
sphinx_theme_builder/_internal/.mypy_cache/3.11/_compression.meta.json
sphinx_theme_builder/_internal/.mypy_cache/3.11/_ctypes.data.json
sphinx_theme_builder/_internal/.mypy_cache/3.11/_ctypes.meta.json
sphinx_theme_builder/_internal/.mypy_cache/3.11/_decimal.data.json
sphinx_theme_builder/_internal/.mypy_cache/3.11/_decimal.meta.json
sphinx_theme_builder/_internal/.mypy_cache/3.11/_operator.data.json
sphinx_theme_builder/_internal/.mypy_cache/3.11/_operator.meta.json
sphinx_theme_builder/_internal/.mypy_cache/3.11/_random.data.json
sphinx_theme_builder/_internal/.mypy_cache/3.11/_random.meta.json
sphinx_theme_builder/_internal/.mypy_cache/3.11/_thread.data.json
sphinx_theme_builder/_internal/.mypy_cache/3.11/_thread.meta.json
sphinx_theme_builder-0.3.2.dist-info/entry_points.txt
sphinx_theme_builder-0.3.2.dist-info/licenses/LICENSE
sphinx_theme_builder-0.3.2.dist-info/WHEEL
sphinx_theme_builder-0.3.2.dist-info/METADATA
sphinx_theme_builder-0.3.2.dist-info/RECORD
