Metadata-Version: 2.4
Name: sphinx-theme-builder
Version: 0.3.2
Summary: A tool for authoring Sphinx themes with a simple (opinionated) workflow.
Author-email: Pradyun Gedam <mail@pradyunsg.me>
Requires-Python: >=3.10
Classifier: Development Status :: 2 - Pre-Alpha
Classifier: Framework :: Sphinx
Classifier: Intended Audience :: Developers
Classifier: License :: OSI Approved :: MIT License
Classifier: Operating System :: OS Independent
Classifier: Programming Language :: Python :: 3.10
Classifier: Programming Language :: Python :: 3.11
Classifier: Programming Language :: Python :: 3.12
Classifier: Programming Language :: Python :: 3.13
Classifier: Programming Language :: Python :: 3.14
Classifier: Programming Language :: Python :: 3
Classifier: Topic :: Documentation
Classifier: Topic :: Software Development :: Documentation
Classifier: Topic :: Software Development :: Libraries :: Python Modules
License-File: LICENSE
Requires-Dist: pyproject-metadata >= 0.10.0
Requires-Dist: packaging
Requires-Dist: rich
Requires-Dist: nodeenv
Requires-Dist: setuptools
Requires-Dist: tomli ; python_version < '3.11'
Requires-Dist: diagnostic>=2
Requires-Dist: build ; extra == "cli"
Requires-Dist: click ; extra == "cli"
Requires-Dist: sphinx-autobuild ; extra == "cli"
Project-URL: Documentation, https://sphinx-theme-builder.readthedocs.io/en/latest/
Project-URL: Source, https://github.com/pradyunsg/sphinx-theme-builder
Provides-Extra: cli
